discordsdk/__init__.py
discordsdk/achievement.py
discordsdk/activity.py
discordsdk/application.py
discordsdk/discord.py
discordsdk/enum.py
discordsdk/event.py
discordsdk/exception.py
discordsdk/image.py
discordsdk/lobby.py
discordsdk/model.py
discordsdk/network.py
discordsdk/overlay.py
discordsdk/relationship.py
discordsdk/sdk.py
discordsdk/storage.py
discordsdk/store.py
discordsdk/user.py
discordsdk/voice.py
discordsdk-0.2.5.dist-info/LICENSE
discordsdk-0.2.5.dist-info/METADATA
discordsdk-0.2.5.dist-info/WHEEL
discordsdk-0.2.5.dist-info/top_level.txt
discordsdk-0.2.5.dist-info/RECORD
