Metadata-Version: 2.1
Name: discordsdk
Version: 0.2.5
Summary: Python wrapper around Discord's Game SDK library.
Home-page: https://github.com/LennyPhoenix/py-discord-sdk
Author: LennyPhoenix & NathaanTFM
Author-email: lennyphoenixc@gmail.com
License: LICENSE
Platform: UNKNOWN
Classifier: Programming Language :: Python :: 3
Classifier: License :: OSI Approved :: MIT License
Classifier: Operating System :: OS Independent
Requires-Python: >= 3.5
License-File: LICENSE
